tendenci
