Metadata-Version: 2.4
Name: tendenci
Version: 15.3.12
Summary: Tendenci - The Open Source Association Management System (AMS)
Author-email: Tendenci <programmers@tendenci.com>
License: Tendenci - Content Management System (CMS) built for non-profits
Project-URL: Homepage, https://github.com/tendenci/tendenci/
Project-URL: Documentation, https://tendenci.readthedocs.io/en/latest/
Project-URL: Repository, https://github.com/tendenci/tendenci/
Project-URL: Issues, https://github.com/tendenci/tendenci/issues
Project-URL: Changelog, https://github.com/tendenci/tendenci/blob/main/CHANGELOG.md
Project-URL: Funding, https://www.tendenci.com/donations/
Classifier: Development Status :: 5 - Production/Stable
Classifier: Environment :: Web Environment
Classifier: Framework :: Django
Classifier: Framework :: Django :: 4.2
Classifier: Intended Audience :: Developers
Classifier: Intended Audience :: End Users/Desktop
Classifier: Intended Audience :: Information Technology
Classifier: Natural Language :: English
Classifier: Operating System :: OS Independent
Classifier: Programming Language :: Python
Classifier: Programming Language :: Python :: 3.8
Classifier: Programming Language :: Python :: 3.9
Classifier: Programming Language :: Python :: 3.10
Classifier: Programming Language :: Python :: 3.11
Classifier: Programming Language :: Python :: 3.12
Classifier: Programming Language :: Python :: 3.13
Classifier: Topic :: Internet :: WWW/HTTP
Classifier: Topic :: Internet :: WWW/HTTP :: Dynamic Content
Classifier: Topic :: Internet :: WWW/HTTP :: WSGI
Classifier: Topic :: Internet :: WWW/HTTP :: WSGI :: Application
Requires-Python: >=3.8
License-File: LICENSE
Requires-Dist: future
Requires-Dist: six
Requires-Dist: configparser
Requires-Dist: Django<5.0,>=4.2
Requires-Dist: django-formtools>=2.5.1
Requires-Dist: Pillow==10.3.0
Requires-Dist: django-countries==7.5.1
Requires-Dist: django-localflavor==4.0
Requires-Dist: dj-pagination>=2.5.0
Requires-Dist: django-picklefield>=3.2
Requires-Dist: django-simple-captcha==0.6.0
Requires-Dist: tendenci-django-tagging==0.6
Requires-Dist: django-haystack==3.3.0
Requires-Dist: django-debug-toolbar>=3.4.0
Requires-Dist: django-sql-explorer==3.2.1
Requires-Dist: django-apptemplates>=1.5
Requires-Dist: feedparser>=6.0.11
Requires-Dist: pytz==2023.3
Requires-Dist: simplejson>=3.19.2
Requires-Dist: webcolors>=1.13
Requires-Dist: xlrd3>=1.1.0
Requires-Dist: xlwt>=1.3.0
Requires-Dist: beautifulsoup4==4.12.3
Requires-Dist: createsend==7.0.0
Requires-Dist: celery==5.3.6
Requires-Dist: mimeparse>=0.1.3
Requires-Dist: python-dateutil==2.8.2
Requires-Dist: pdfminer.six==20231228
Requires-Dist: stripe==7.13.0
Requires-Dist: pycryptodome==3.20.0
Requires-Dist: boto3==1.34.23
Requires-Dist: django-timezone-field==6.1.0
Requires-Dist: django-ses==3.5.2
Requires-Dist: django-tastypie==0.15.1
Requires-Dist: docutils==0.20
Requires-Dist: chardet==5.2.0
Requires-Dist: psycopg2==2.9.9
Requires-Dist: gunicorn==23.0.0
Requires-Dist: gevent==23.9.1
Requires-Dist: django-storages==1.14.2
Requires-Dist: Whoosh==2.7.4
Requires-Dist: simple-salesforce==1.12.6
Requires-Dist: selenium==4.16.0
Requires-Dist: raven==6.10.0
Requires-Dist: tendenci-django-admin-bootstrapped>=5.2
Requires-Dist: django-bootstrap3==23.6
Requires-Dist: unidecode
Requires-Dist: Markdown==3.7
Requires-Dist: bleach>=6.1.0
Requires-Dist: django-bootstrap-form<4,>=3.1
Requires-Dist: email-reply-parser
Requires-Dist: django-markdown-deux
Requires-Dist: xhtml2pdf==0.2.17
Requires-Dist: reportlab==4.2.2
Requires-Dist: python-magic
Requires-Dist: nameparser
Requires-Dist: Authlib==1.3.1
Requires-Dist: django-admin-rangefilter==0.13.2
Requires-Dist: django-q2==1.6.2
Requires-Dist: pymemcache>=4.0.0
Requires-Dist: django-two-factor-auth>=1.15.5
Requires-Dist: phonenumbers>=8.13.28
Requires-Dist: django-qr-code==3.1.1
Requires-Dist: pyzoom>=1.0.5
Requires-Dist: PyJWT>=2.8.0
Requires-Dist: django-model-utils>=4.3.1
Requires-Dist: model-bakery==1.17.0
Requires-Dist: httplib2==0.22.0
Requires-Dist: phonenumberslite
Dynamic: license-file
